eggfreezer.py
setup.cfg
setup.py
EggFreezer.egg-info/PKG-INFO
EggFreezer.egg-info/SOURCES.txt
EggFreezer.egg-info/dependency_links.txt
EggFreezer.egg-info/entry_points.txt
EggFreezer.egg-info/requires.txt
EggFreezer.egg-info/top_level.txt
EggFreezer.egg-info/zip-safe