Metadata-Version: 1.0
Name: EggFreezer
Version: 0.1.6
Summary: Creates single-file installers for eggified distributions
Home-page: UNKNOWN
Author: Alberto Valverde Gonzalez
Author-email: alberto@toscat.net
License: MIT
Download-URL: http://toscawidgets.org/download
Platform: UNKNOWN
